Metadata-Version: 2.1
Name: dig_ass_ep_protos
Version: 2.2.2
Summary: Proto files for dig_ass_ep_protos
Author: AGI-MED-TEAM
Requires-Dist: grpcio ==1.62.1
Requires-Dist: grpcio-tools ==1.62.1
Requires-Dist: agi-med-protos ==0.0.1
